python_auditory_toolbox/auditory_toolbox.py
python_auditory_toolbox/auditory_toolbox_comparison_test.py
python_auditory_toolbox/auditory_toolbox_jax.py
python_auditory_toolbox/auditory_toolbox_jax_test.py
python_auditory_toolbox/auditory_toolbox_test.py
python_auditory_toolbox/auditory_toolbox_torch.py
python_auditory_toolbox/auditory_toolbox_torch_test.py
python_auditory_toolbox-1.0.6.dist-info/LICENSE.txt
python_auditory_toolbox-1.0.6.dist-info/METADATA
python_auditory_toolbox-1.0.6.dist-info/WHEEL
python_auditory_toolbox-1.0.6.dist-info/top_level.txt
python_auditory_toolbox-1.0.6.dist-info/RECORD
