Metadata-Version: 2.1
Name: python_auditory_toolbox
Version: 1.0.6
Summary: Several simple auditory models in JAX, Numpy and Torch
Home-page: https://github.com/MalcolmSlaney/python_auditory_toolbox
Author: Malcolm Slaney
Author-email: malcolm@ieee.org
Classifier: Programming Language :: Python :: 3
Classifier: License :: OSI Approved :: Apache Software License
Classifier: Operating System :: OS Independent
Classifier: Topic :: Multimedia :: Sound/Audio :: Analysis
Requires-Python: >=3.6
License-File: LICENSE.txt
Requires-Dist: absl-py
Requires-Dist: numpy
Requires-Dist: jax
Requires-Dist: jaxlib
Requires-Dist: matplotlib
Requires-Dist: scipy
Requires-Dist: torch
Requires-Dist: torchaudio
